cvat_connector/__init__.py
cvat_connector/cvat_connector.py
cvat_connector/cvat_urls.py
cvat_connector/release.py
cvat_connector-0.1.0.dist-info/LICENSE
cvat_connector-0.1.0.dist-info/METADATA
cvat_connector-0.1.0.dist-info/WHEEL
cvat_connector-0.1.0.dist-info/top_level.txt
cvat_connector-0.1.0.dist-info/RECORD
