Metadata-Version: 2.1
Name: cvat-connector
Version: 0.1.0
Summary: CVAT API Client
Home-page: https://gitlab.com/ouvaco/cvat-connector
Author: Cagdas Bas <cagdas@ouva.co>
Author-email: cagdas@ouva.co
License: UNKNOWN
Platform: UNKNOWN
Classifier: Development Status :: 5 - Production/Stable
Classifier: Intended Audience :: Developers
Classifier: Natural Language :: English
Classifier: License :: OSI Approved :: Apache Software License
Classifier: Programming Language :: Python
Classifier: Programming Language :: Python :: 3
Classifier: Programming Language :: Python :: 3.6
Classifier: Programming Language :: Python :: 3.7
Classifier: Programming Language :: Python :: 3.8
Classifier: Programming Language :: Python :: 3.9
Requires-Python: >=3.6
License-File: LICENSE
Requires-Dist: requests
Requires-Dist: requests-toolbelt
Requires-Dist: dataclass
